Metadata-Version: 2.1
Name: multi-armed-thompson
Version: 0.1
Summary: Thompson sampling for multi-armed bandit
Home-page: https://github.com/tbagnoli/multi_armed_thompson/
Author: Tullio Bagnoli
Author-email: tullio.bagnoli@protonmail.com
License: MIT
Download-URL: https://github.com/tbagnoli/multi_armed_thompson/archive/v_01.tar.gz
Keywords: thompson,sampling,unsupervised
Platform: UNKNOWN
Classifier: Programming Language :: Python :: 3
Classifier: License :: OSI Approved :: MIT License
Classifier: Operating System :: OS Independent
Requires-Python: >=3.7
